scpeftreproduction/transformers/__init__.py
scpeftreproduction/transformers/activations.py
scpeftreproduction/transformers/activations_tf.py
scpeftreproduction/transformers/audio_utils.py
scpeftreproduction/transformers/benchmark/__init__.py
scpeftreproduction/transformers/benchmark/benchmark.py
scpeftreproduction/transformers/benchmark/benchmark_args.py
scpeftreproduction/transformers/benchmark/benchmark_args_tf.py
scpeftreproduction/transformers/benchmark/benchmark_args_utils.py
scpeftreproduction/transformers/benchmark/benchmark_tf.py
scpeftreproduction/transformers/benchmark/benchmark_utils.py
scpeftreproduction/transformers/commands/__init__.py
scpeftreproduction/transformers/commands/add_new_model.py
scpeftreproduction/transformers/commands/add_new_model_like.py
scpeftreproduction/transformers/commands/convert.py
scpeftreproduction/transformers/commands/download.py
scpeftreproduction/transformers/commands/env.py
scpeftreproduction/transformers/commands/lfs.py
scpeftreproduction/transformers/commands/pt_to_tf.py
scpeftreproduction/transformers/commands/run.py
scpeftreproduction/transformers/commands/serving.py
scpeftreproduction/transformers/commands/train.py
scpeftreproduction/transformers/commands/transformers_cli.py
scpeftreproduction/transformers/commands/user.py
scpeftreproduction/transformers/configuration_utils.py
scpeftreproduction/transformers/convert_graph_to_onnx.py
scpeftreproduction/transformers/convert_pytorch_checkpoint_to_tf2.py
scpeftreproduction/transformers/convert_slow_tokenizer.py
scpeftreproduction/transformers/convert_slow_tokenizers_checkpoints_to_fast.py
scpeftreproduction/transformers/convert_tf_hub_seq_to_seq_bert_to_pytorch.py
scpeftreproduction/transformers/data/__init__.py
scpeftreproduction/transformers/data/data_collator.py
scpeftreproduction/transformers/data/datasets/__init__.py
scpeftreproduction/transformers/data/datasets/glue.py
scpeftreproduction/transformers/data/datasets/language_modeling.py
scpeftreproduction-0.0.3.dist-info/METADATA
scpeftreproduction-0.0.3.dist-info/WHEEL
scpeftreproduction-0.0.3.dist-info/RECORD
